handwriting_features/__init__.py
handwriting_features/data/__init__.py
handwriting_features/data/containers/__init__.py
handwriting_features/data/containers/sample.py
handwriting_features/data/descriptors/__init__.py
handwriting_features/data/descriptors/statistics.py
handwriting_features/data/exceptions/__init__.py
handwriting_features/data/exceptions/dsp.py
handwriting_features/data/exceptions/sample.py
handwriting_features/data/exceptions/statistics.py
handwriting_features/data/utils/__init__.py
handwriting_features/data/utils/cleanup.py
handwriting_features/data/utils/dsp.py
handwriting_features/data/utils/iteration.py
handwriting_features/data/utils/math.py
handwriting_features/features/__init__.py
handwriting_features/features/base.py
handwriting_features/features/interface.py
handwriting_features/features/configuration/__init__.py
handwriting_features/features/configuration/mapping.py
handwriting_features/features/configuration/settings.py
handwriting_features/features/exceptions/__init__.py
handwriting_features/features/exceptions/mapping.py
handwriting_features/features/exceptions/validation.py
handwriting_features/features/implementation/__init__.py
handwriting_features/features/implementation/conventional/__init__.py
handwriting_features/features/implementation/conventional/composite.py
handwriting_features/features/implementation/conventional/dynamic.py
handwriting_features/features/implementation/conventional/kinematic.py
handwriting_features/features/implementation/conventional/spatial.py
handwriting_features/features/implementation/conventional/temporal.py
handwriting_features/features/implementation/conventional/utils/__init__.py
handwriting_features/features/implementation/conventional/utils/composite.py
handwriting_features/features/implementation/conventional/utils/dynamic.py
handwriting_features/features/implementation/conventional/utils/kinematic.py
handwriting_features/features/implementation/conventional/utils/spatial.py
handwriting_features-1.0.9.dist-info/LICENSE
handwriting_features-1.0.9.dist-info/METADATA
handwriting_features-1.0.9.dist-info/WHEEL
handwriting_features-1.0.9.dist-info/top_level.txt
handwriting_features-1.0.9.dist-info/RECORD
